komodoro/__init__.py
komodoro/params.py
komodoro-0.1.0.dist-info/METADATA
komodoro-0.1.0.dist-info/WHEEL
komodoro-0.1.0.dist-info/RECORD
